hh_jira_mcp_server/__init__.py
hh_jira_mcp_server/server.py
hh_jira_mcp_server/utils.py
hh_jira_mcp_server-0.1.0.dist-info/METADATA
hh_jira_mcp_server-0.1.0.dist-info/WHEEL
hh_jira_mcp_server-0.1.0.dist-info/entry_points.txt
hh_jira_mcp_server-0.1.0.dist-info/RECORD
