Metadata-Version: 2.3
Name: hh-jira-mcp-server
Version: 0.1.0
Summary: A MCP server project
Author-email: Alexey Dubinin <a.dubinin@hh.ru>
Requires-Python: >=3.13
Requires-Dist: fastmcp>=0.3.3
Requires-Dist: jira>=3.8.0
Requires-Dist: keyring>=25.5.0
Requires-Dist: mcp>=1.0.0
